collocater/__init__.py
collocater/collocater.py
collocater/generateObject.py
collocater/data/collocater_obj.joblib
collocater/data/collocations_dict.joblib
collocater/data/irr_verbs_dict.joblib
collocater/data/prepositions.joblib
collocater-0.3.dist-info/LICENSE
collocater-0.3.dist-info/METADATA
collocater-0.3.dist-info/WHEEL
collocater-0.3.dist-info/top_level.txt
collocater-0.3.dist-info/RECORD
