Metadata-Version: 2.1
Name: collocater
Version: 0.3
Summary: Package for retrieving collocations from text with Spacy
Home-page: https://github.com/rtapiaoregui/collocater
Author: Rita Tapia Oregui
Author-email: rtapiaoregui@gmail.com
License: UNKNOWN
Keywords: Collocations Finder
Platform: UNKNOWN
Requires-Dist: beautifulsoup4 (>=4.6.3)
Requires-Dist: joblib (>=0.14.1)
Requires-Dist: lxml (>=4.2.5)
Requires-Dist: pandas (>=1.0.1)
Requires-Dist: regex (>=2018.1.10)
Requires-Dist: requests (>=2.21.0)
Requires-Dist: spacy (>=2.2.3)
